README.md
setup.cfg
setup.py
alphabox/__init__.py
alphabox/experiment.py
alphabox.egg-info/PKG-INFO
alphabox.egg-info/SOURCES.txt
alphabox.egg-info/dependency_links.txt
alphabox.egg-info/not-zip-safe
alphabox.egg-info/requires.txt
alphabox.egg-info/top_level.txt